byproxy/__init__.py
byproxy/proxy_checker/__init__.py
byproxy/proxy_maker/__init__.py
CHANGELOG.md
byproxy-0.1.5.dist-info/LICENSE
byproxy-0.1.5.dist-info/WHEEL
byproxy-0.1.5.dist-info/METADATA
byproxy-0.1.5.dist-info/RECORD
